odoo/addons/ssi_accountant_general_audit_ws_ra220/README.rst
odoo/addons/ssi_accountant_general_audit_ws_ra220/__init__.py
odoo/addons/ssi_accountant_general_audit_ws_ra220/__manifest__.py
odoo/addons/ssi_accountant_general_audit_ws_ra220/data/accountant_assersion_type_data.xml
odoo/addons/ssi_accountant_general_audit_ws_ra220/data/accountant_general_audit_worksheet_conclusion_data.xml
odoo/addons/ssi_accountant_general_audit_ws_ra220/data/accountant_general_audit_worksheet_type_data.xml
odoo/addons/ssi_accountant_general_audit_ws_ra220/data/approval_template_data.xml
odoo/addons/ssi_accountant_general_audit_ws_ra220/data/ir_sequence_data.xml
odoo/addons/ssi_accountant_general_audit_ws_ra220/data/policy_template_data.xml
odoo/addons/ssi_accountant_general_audit_ws_ra220/data/sequence_template_data.xml
odoo/addons/ssi_accountant_general_audit_ws_ra220/models/__init__.py
odoo/addons/ssi_accountant_general_audit_ws_ra220/models/accountant_assersion_type.py
odoo/addons/ssi_accountant_general_audit_ws_ra220/models/accountant_general_audit_standard_detail.py
odoo/addons/ssi_accountant_general_audit_ws_ra220/models/ws_ra220.py
odoo/addons/ssi_accountant_general_audit_ws_ra220/models/ws_ra2201.py
odoo/addons/ssi_accountant_general_audit_ws_ra220/models/ws_ra22011.py
odoo/addons/ssi_accountant_general_audit_ws_ra220/models/ws_ra22012.py
odoo/addons/ssi_accountant_general_audit_ws_ra220/models/ws_ra2202.py
odoo/addons/ssi_accountant_general_audit_ws_ra220/models/ws_ra22021.py
odoo/addons/ssi_accountant_general_audit_ws_ra220/models/ws_ra22021_account_cycle.py
odoo/addons/ssi_accountant_general_audit_ws_ra220/models/ws_ra22021_cycle_detail.py
odoo/addons/ssi_accountant_general_audit_ws_ra220/models/ws_ra2202_control_risk.py
odoo/addons/ssi_accountant_general_audit_ws_ra220/models/ws_ra2203.py
odoo/addons/ssi_accountant_general_audit_ws_ra220/models/ws_ra2203_account_control_activity.py
odoo/addons/ssi_accountant_general_audit_ws_ra220/models/ws_ra2203_account_cycle.py
odoo14_addon_ssi_accountant_general_audit_ws_ra220-14.0.1.3.2.dev1.dist-info/METADATA
odoo14_addon_ssi_accountant_general_audit_ws_ra220-14.0.1.3.2.dev1.dist-info/WHEEL
odoo14_addon_ssi_accountant_general_audit_ws_ra220-14.0.1.3.2.dev1.dist-info/top_level.txt
odoo14_addon_ssi_accountant_general_audit_ws_ra220-14.0.1.3.2.dev1.dist-info/RECORD
